password_generator/__init__.py
password_generator/apps.py
password_generator/cli.py
password_generator/generator.py
password_generator/urls.py
password_generator/views.py
acces_generator-1.0.0.dist-info/METADATA
acces_generator-1.0.0.dist-info/WHEEL
acces_generator-1.0.0.dist-info/entry_points.txt
acces_generator-1.0.0.dist-info/top_level.txt
acces_generator-1.0.0.dist-info/RECORD
