Metadata-Version: 2.4
Name: acces-generator
Version: 1.0.0
Summary: Un générateur de mots de passe sécurisé en ligne de commande et en Python
Author: Momo
Author-email: omomo9414@gmail.com
License: MIT
Classifier: Programming Language :: Python :: 3
Classifier: License :: OSI Approved :: MIT License
Classifier: Environment :: Console
Classifier: Operating System :: OS Independent
Requires-Python: >=3.6
Dynamic: author
Dynamic: author-email
Dynamic: classifier
Dynamic: description
Dynamic: description-content-type
Dynamic: license
Dynamic: requires-python
Dynamic: summary
